analytic_models/__init__.py
analytic_models/actions.py
analytic_models/autotests.py
analytic_models/battles.py
analytic_models/db.py
analytic_models/events.py
analytic_models/fields.py
analytic_models/guilds.py
analytic_models/profiles.py
analytic_models/purchases.py
analytic_models/raids.py
analytic_models/rewards.py
analytic_models/utils.py
panoramik_analytic_models-0.3.6.dist-info/METADATA
panoramik_analytic_models-0.3.6.dist-info/WHEEL
panoramik_analytic_models-0.3.6.dist-info/top_level.txt
panoramik_analytic_models-0.3.6.dist-info/RECORD
