Metadata-Version: 2.1
Name: panoramik-analytic-models
Version: 0.3.6
Summary: Panoramik ClickHouse analytic models
Home-page: https://bitbucket.org/panoramik/analytic_models
Author: Panoramik
Author-email: panormaikinc@gmail.com
License: Proprietary
Platform: UNKNOWN
Classifier: Programming Language :: Python :: 3
Classifier: License :: Other/Proprietary License
Classifier: Operating System :: OS Independent
Requires-Dist: infi.clickhouse-orm (>=1.0.3)
